{
  "2026-05-04 07:00": {
    "R1/C1": {
      "hippodrome": "VICHY",
      "label": "PRIX DE DOMPIERRE SUR BESBRE",
      "heure": "10:00",
      "horses": {
        "#1 HAPPY JAVANAIS": {
          "odds": 51.0,
          "tendance": "+",
          "magnitude": 1.57,
          "favoris": false
        },
        "#2 ISKILIPIPY BRIAIRE": {
          "odds": 31.0,
          "tendance": "+",
          "magnitude": 3.25,
          "favoris": false
        },
        "#3 KANELLE DU VAL": {
          "odds": 7.3,
          "tendance": "",
          "magnitude": 0.0,
          "favoris": false
        },
        "#4 KELLY DE CERISY": {
          "odds": 29.0,
          "tendance": "-",
          "magnitude": -1.67,
          "favoris": false
        },
        "#5 KARAYAN DES IRIS": {
          "odds": 23.0,
          "tendance": "+",
          "magnitude": 4.05,
          "favoris": false
        },
        "#6 JOYAU DAIRPET": {
          "odds": 6.5,
          "tendance": "+",
          "magnitude": 12.06,
          "favoris": false
        },
        "#7 FIGARO DE BUSSET": {
          "odds": 49.0,
          "tendance": "-",
          "magnitude": -2.76,
          "favoris": false
        },
        "#8 ILEX DE CABERT": {
          "odds": 8.8,
          "tendance": "+",
          "magnitude": 7.31,
          "favoris": false
        },
        "#9 I LOVE ELDE": {
          "odds": 3.9,
          "tendance": "",
          "magnitude": 0.0,
          "favoris": true
        },
        "#10 JOBALASKO BLEU": {
          "odds": 4.3,
          "tendance": "+",
          "magnitude": 2.38,
          "favoris": false
        },
        "#11 IDEAL DE BANNES": {
          "odds": 16.0,
          "tendance": "-",
          "magnitude": -21.18,
          "favoris": false
        },
        "#12 GOLDEN VIKING": {
          "odds": 66.0,
          "tendance": "-",
          "magnitude": -28.19,
          "favoris": false
        },
        "#13 KIMBO BERRY": {
          "odds": 18.0,
          "tendance": "-",
          "magnitude": -33.09,
          "favoris": false
        }
      }
    },
    "R1/C2": {
      "hippodrome": "VICHY",
      "label": "PRIX DE SAINT DIDIER LA FORET",
      "heure": "10:35",
      "horses": {
        "#1 NOW OAKS": {
          "odds": 97.0,
          "tendance": "-",
          "magnitude": -21.23,
          "favoris": false
        },
        "#2 NOWAK DE BUSSET": {
          "odds": 24.0,
          "tendance": "-",
          "magnitude": -21.1,
          "favoris": false
        },
        "#3 NIAGARA DU LOISIR": {
          "odds": 50.0,
          "tendance": "-",
          "magnitude": -7.84,
          "favoris": false
        },
        "#4 NELSON VOLTIGEUR": {
          "odds": 23.0,
          "tendance": "+",
          "magnitude": 1.27,
          "favoris": false
        },
        "#5 N'ATTENDS PERSONNE": {
          "odds": 25.0,
          "tendance": "-",
          "magnitude": -0.39,
          "favoris": false
        },
        "#6 NEPAL MISA": {
          "odds": 12.0,
          "tendance": "+",
          "magnitude": 25.51,
          "favoris": false
        },
        "#7 NEPTUNE AU VENT": {
          "odds": 13.0,
          "tendance": "+",
          "magnitude": 9.75,
          "favoris": false
        },
        "#8 NABUCCO BLUES": {
          "odds": 6.0,
          "tendance": "+",
          "magnitude": 13.2,
          "favoris": false
        },
        "#9 NUNZIATA": {
          "odds": 34.0,
          "tendance": "-",
          "magnitude": -10.02,
          "favoris": false
        },
        "#10 NESTOR DI MOKO": {
          "odds": 9.1,
          "tendance": "-",
          "magnitude": -52.35,
          "favoris": false
        },
        "#11 NEW ATOUT": {
          "odds": 6.9,
          "tendance": "+",
          "magnitude": 15.0,
          "favoris": false
        },
        "#12 NIEHKU": {
          "odds": 2.4,
          "tendance": "",
          "magnitude": 0.0,
          "favoris": true
        }
      }
    },
    "R1/C3": {
      "hippodrome": "VICHY",
      "label": "PRIX DE SANSSAT",
      "heure": "11:10",
      "horses": {
        "#1 KING KONG SMILE": {
          "odds": 15.0,
          "tendance": "+",
          "magnitude": 15.21,
          "favoris": false
        },
        "#2 JIFF DES CELLIERS": {
          "odds": 116.0,
          "tendance": "-",
          "magnitude": -10.14,
          "favoris": false
        },
        "#3 KYSKO DE FAEL": {
          "odds": 32.0,
          "tendance": "+",
          "magnitude": 5.96,
          "favoris": false
        },
        "#4 KAHIRA DES MARES": {
          "odds": 16.0,
          "tendance": "-",
          "magnitude": -16.41,
          "favoris": false
        },
        "#5 JADE FOR EVER": {
          "odds": 30.0,
          "tendance": "+",
          "magnitude": 12.31,
          "favoris": false
        },
        "#6 KOMAN": {
          "odds": 17.0,
          "tendance": "+",
          "magnitude": 2.89,
          "favoris": false
        },
        "#7 KANARY BAY": {
          "odds": 33.0,
          "tendance": "+",
          "magnitude": 13.74,
          "favoris": false
        },
        "#8 JAMES RULES": {
          "odds": 26.0,
          "tendance": "-",
          "magnitude": -0.37,
          "favoris": false
        },
        "#9 KEYSTONE OAKS": {
          "odds": 116.0,
          "tendance": "-",
          "magnitude": -3.22,
          "favoris": false
        },
        "#10 KADO DES MOLLES": {
          "odds": 36.0,
          "tendance": "-",
          "magnitude": -18.87,
          "favoris": false
        },
        "#11 KING TRACK": {
          "odds": 1.3,
          "tendance": "",
          "magnitude": 0.0,
          "favoris": true
        },
        "#12 KADOR D'ESPACE": {
          "odds": 55.0,
          "tendance": "+",
          "magnitude": 1.28,
          "favoris": false
        },
        "#13 KELBELLE MOIRE": {
          "odds": 16.0,
          "tendance": "+",
          "magnitude": 5.96,
          "favoris": false
        },
        "#14 KAPITANO DE LOU": {
          "odds": 90.0,
          "tendance": "-",
          "magnitude": -3.83,
          "favoris": false
        },
        "#15 KEOPS DES CELLIERS": {
          "odds": 662.0,
          "tendance": "+",
          "magnitude": 17.5,
          "favoris": false
        },
        "#16 KERIA FLEURY": {
          "odds": 88.0,
          "tendance": "+",
          "magnitude": 7.03,
          "favoris": false
        }
      }
    },
    "R1/C4": {
      "hippodrome": "VICHY",
      "label": "PRIX HENRI BERRY",
      "heure": "11:55",
      "horses": {
        "#1 ONE LOVE BIANCA": {
          "odds": 72.0,
          "tendance": "+",
          "magnitude": 18.24,
          "favoris": false
        },
        "#2 INVADER AM": {
          "odds": 58.0,
          "tendance": "-",
          "magnitude": -17.14,
          "favoris": false
        },
        "#3 FEROX BRICK": {
          "odds": 6.4,
          "tendance": "+",
          "magnitude": 4.91,
          "favoris": false
        },
        "#4 ISENGRINE ABSOLUTE": {
          "odds": 23.0,
          "tendance": "-",
          "magnitude": -0.84,
          "favoris": false
        },
        "#5 HERMES SCOTT": {
          "odds": 68.0,
          "tendance": "-",
          "magnitude": -1.01,
          "favoris": false
        },
        "#6 ADAMO DIPA": {
          "odds": 22.0,
          "tendance": "-",
          "magnitude": -0.43,
          "favoris": false
        },
        "#7 CERTAINLY (SWE)": {
          "odds": 28.0,
          "tendance": "-",
          "magnitude": -14.32,
          "favoris": false
        },
        "#8 HELMA DE BUSSET": {
          "odds": 14.0,
          "tendance": "+",
          "magnitude": 0.67,
          "favoris": false
        },
        "#9 HAPPY PACHA": {
          "odds": 33.0,
          "tendance": "-",
          "magnitude": -6.98,
          "favoris": false
        },
        "#10 HOLDING GIRL": {
          "odds": 16.0,
          "tendance": "+",
          "magnitude": 8.38,
          "favoris": false
        },
        "#11 HERMES LUDOIS": {
          "odds": 14.0,
          "tendance": "",
          "magnitude": 0.0,
          "favoris": false
        },
        "#12 GENERAL DU NORD": {
          "odds": 76.0,
          "tendance": "+",
          "magnitude": 10.98,
          "favoris": false
        },
        "#13 ISTORIC MAUZUN": {
          "odds": 2.9,
          "tendance": "-",
          "magnitude": -3.33,
          "favoris": true
        },
        "#14 IQUEM D'AMER": {
          "odds": 14.0,
          "tendance": "+",
          "magnitude": 4.41,
          "favoris": false
        },
        "#15 HARMONY LA NUIT": {
          "odds": 15.0,
          "tendance": "",
          "magnitude": 0.0,
          "favoris": false
        },
        "#16 ICARE WILLIAMS": {
          "odds": 7.3,
          "tendance": "-",
          "magnitude": -1.35,
          "favoris": false
        }
      }
    },
    "R1/C5": {
      "hippodrome": "VICHY",
      "label": "PRIX DU VERNET",
      "heure": "12:30",
      "horses": {
        "#1 MANDARINO FLEURY": {
          "odds": 36.0,
          "tendance": "+",
          "magnitude": 2.21,
          "favoris": false
        },
        "#2 MILADY OAKS": {
          "odds": 47.0,
          "tendance": "+",
          "magnitude": 17.45,
          "favoris": false
        },
        "#3 MADE IN MOIRE": {
          "odds": 26.0,
          "tendance": "+",
          "magnitude": 10.41,
          "favoris": false
        },
        "#4 MISTRAL DU PORET": {
          "odds": 26.0,
          "tendance": "+",
          "magnitude": 2.71,
          "favoris": false
        },
        "#5 MOKY BERRY": {
          "odds": 17.0,
          "tendance": "-",
          "magnitude": -16.26,
          "favoris": false
        },
        "#6 MIMI WILLIAMS": {
          "odds": 26.0,
          "tendance": "+",
          "magnitude": 17.77,
          "favoris": false
        },
        "#7 MELKIOR CASTELLE": {
          "odds": 11.0,
          "tendance": "-",
          "magnitude": -17.73,
          "favoris": false
        },
        "#8 MAESTRO CELO": {
          "odds": 11.0,
          "tendance": "",
          "magnitude": 0.0,
          "favoris": false
        },
        "#9 MERRY CHRISTMAS": {
          "odds": 4.6,
          "tendance": "+",
          "magnitude": 12.19,
          "favoris": false
        },
        "#10 MAGIC INSTINCT": {
          "odds": 5.6,
          "tendance": "",
          "magnitude": 0.0,
          "favoris": false
        },
        "#11 MANDARINA DE LOU": {
          "odds": 4.4,
          "tendance": "-",
          "magnitude": -8.33,
          "favoris": true
        },
        "#12 MEMPHIS ELLIS": {
          "odds": 6.4,
          "tendance": "-",
          "magnitude": -1.53,
          "favoris": false
        }
      }
    },
    "R1/C6": {
      "hippodrome": "VICHY",
      "label": "PRIX D'ECHASSIERES",
      "heure": "13:05",
      "horses": {
        "#1 JADE HERINIERE": {
          "odds": 9.9,
          "tendance": "+",
          "magnitude": 6.45,
          "favoris": false
        },
        "#2 IDYLLE EVER": {
          "odds": 15.0,
          "tendance": "+",
          "magnitude": 4.13,
          "favoris": false
        },
        "#3 JALBA DU FER": {
          "odds": 7.1,
          "tendance": "-",
          "magnitude": -13.41,
          "favoris": false
        },
        "#4 IN LOVE GEDE": {
          "odds": 14.0,
          "tendance": "-",
          "magnitude": -6.04,
          "favoris": false
        },
        "#5 HARMONIA THE BEST": {
          "odds": 36.0,
          "tendance": "+",
          "magnitude": 10.42,
          "favoris": false
        },
        "#6 JUSTESS VIKING": {
          "odds": 19.0,
          "tendance": "+",
          "magnitude": 3.22,
          "favoris": false
        },
        "#7 JIVA": {
          "odds": 2.9,
          "tendance": "+",
          "magnitude": 3.57,
          "favoris": true
        },
        "#8 ISCHIA SAINT CLAIR": {
          "odds": 12.0,
          "tendance": "+",
          "magnitude": 3.38,
          "favoris": false
        },
        "#9 JIRARDIERE MERITE": {
          "odds": 5.2,
          "tendance": "-",
          "magnitude": -3.7,
          "favoris": false
        },
        "#10 IN LOVE DE VINDECY": {
          "odds": 34.0,
          "tendance": "+",
          "magnitude": 10.44,
          "favoris": false
        },
        "#11 INDIE DE YOR": {
          "odds": 82.0,
          "tendance": "+",
          "magnitude": 10.6,
          "favoris": false
        },
        "#12 JESSY D'ARCY": {
          "odds": 19.0,
          "tendance": "+",
          "magnitude": 3.1,
          "favoris": false
        }
      }
    },
    "R1/C7": {
      "hippodrome": "VICHY",
      "label": "PRIX D'ABREST",
      "heure": "13:40",
      "horses": {
        "#1 HAMPTON AMERICA": {
          "odds": 55.0,
          "tendance": "+",
          "magnitude": 14.69,
          "favoris": false
        },
        "#2 IF DE LA COUDRE": {
          "odds": 6.0,
          "tendance": "-",
          "magnitude": -14.28,
          "favoris": false
        },
        "#3 JUST HAUFOR": {
          "odds": 6.1,
          "tendance": "+",
          "magnitude": 7.01,
          "favoris": false
        },
        "#4 JENJOY MAYBE": {
          "odds": 4.4,
          "tendance": "+",
          "magnitude": 4.76,
          "favoris": true
        },
        "#5 IZIO D'ECHAL": {
          "odds": 6.6,
          "tendance": "-",
          "magnitude": -4.34,
          "favoris": false
        },
        "#6 HELBERT FOUTEAU": {
          "odds": 7.2,
          "tendance": "+",
          "magnitude": 12.49,
          "favoris": false
        },
        "#7 ILLUSTRE DE CHENOU": {
          "odds": 14.0,
          "tendance": "+",
          "magnitude": 14.75,
          "favoris": false
        },
        "#8 IDEAL GABINLEA": {
          "odds": 36.0,
          "tendance": "+",
          "magnitude": 14.59,
          "favoris": false
        },
        "#9 HAMILTON FOUTEAU": {
          "odds": 29.0,
          "tendance": "+",
          "magnitude": 8.95,
          "favoris": false
        },
        "#10 JOOSTER LE FOL": {
          "odds": 92.0,
          "tendance": "-",
          "magnitude": -61.77,
          "favoris": false
        },
        "#11 IMPACT OAKS": {
          "odds": 46.0,
          "tendance": "-",
          "magnitude": -13.96,
          "favoris": false
        },
        "#12 JAGOAR DU TRIEUX": {
          "odds": 8.1,
          "tendance": "-",
          "magnitude": -22.85,
          "favoris": false
        },
        "#13 ISCO DE JOUDES": {
          "odds": 55.0,
          "tendance": "+",
          "magnitude": 14.69,
          "favoris": false
        }
      }
    },
    "R1/C8": {
      "hippodrome": "VICHY",
      "label": "PRIX DE GANNAT",
      "heure": "14:15",
      "horses": {
        "#1 LA BELLE AFFAIRE": {
          "odds": 67.0,
          "tendance": "+",
          "magnitude": 17.15,
          "favoris": false
        },
        "#2 LAMPEE DES GOUJONS": {
          "odds": 245.0,
          "tendance": "+",
          "magnitude": 17.25,
          "favoris": false
        },
        "#3 LE GRAND MASSIF": {
          "odds": 28.0,
          "tendance": "-",
          "magnitude": -7.09,
          "favoris": false
        },
        "#4 LUCCIANO D'OMAHA": {
          "odds": 22.0,
          "tendance": "-",
          "magnitude": -3.87,
          "favoris": false
        },
        "#5 LARABELLO DE LOU": {
          "odds": 49.0,
          "tendance": "+",
          "magnitude": 5.37,
          "favoris": false
        },
        "#6 LITTLE BOY": {
          "odds": 5.8,
          "tendance": "+",
          "magnitude": 5.45,
          "favoris": false
        },
        "#7 LORENZO BERRY": {
          "odds": 35.0,
          "tendance": "-",
          "magnitude": -3.58,
          "favoris": false
        },
        "#8 LA SPEZIA DE LOU": {
          "odds": 14.0,
          "tendance": "-",
          "magnitude": -7.89,
          "favoris": false
        },
        "#9 L'ESPOIR": {
          "odds": 44.0,
          "tendance": "+",
          "magnitude": 17.36,
          "favoris": false
        },
        "#10 LA STAR DES ISLES": {
          "odds": 7.1,
          "tendance": "-",
          "magnitude": -19.31,
          "favoris": false
        },
        "#11 LOUNA DU LOCHEUR": {
          "odds": 2.6,
          "tendance": "+",
          "magnitude": 13.04,
          "favoris": true
        },
        "#12 L'AMIRAL DIGEO": {
          "odds": 14.0,
          "tendance": "+",
          "magnitude": 6.56,
          "favoris": false
        },
        "#13 LIBERTINE DJOB": {
          "odds": 22.0,
          "tendance": "-",
          "magnitude": -80.92,
          "favoris": false
        },
        "#14 LITTLE WINGS": {
          "odds": 25.0,
          "tendance": "-",
          "magnitude": -3.83,
          "favoris": false
        },
        "#15 LEXINGTON DANICA": {
          "odds": 12.0,
          "tendance": "+",
          "magnitude": 8.03,
          "favoris": false
        }
      }
    },
    "R2/C1": {
      "hippodrome": "COMPIEGNE",
      "label": "PRIX TERI AC",
      "heure": "09:40",
      "horses": {
        "#1 KATELL DES BLINS": {
          "odds": 10.0,
          "tendance": "+",
          "magnitude": 5.0,
          "favoris": false
        },
        "#2 HEMEVOICI": {
          "odds": 7.8,
          "tendance": "-",
          "magnitude": -2.5,
          "favoris": false
        },
        "#3 ELCOND'OR FORLONGE": {
          "odds": 18.0,
          "tendance": "-",
          "magnitude": -20.68,
          "favoris": false
        },
        "#4 CAPE OF LOVE": {
          "odds": 8.5,
          "tendance": "+",
          "magnitude": 4.93,
          "favoris": false
        },
        "#5 GLASGOW DU BERLAIS": {
          "odds": 2.5,
          "tendance": "",
          "magnitude": 0.0,
          "favoris": true
        },
        "#6 NIKO HAS": {
          "odds": 9.5,
          "tendance": "-",
          "magnitude": -4.04,
          "favoris": false
        },
        "#7 GRANDGADOR": {
          "odds": 5.2,
          "tendance": "-",
          "magnitude": -1.88,
          "favoris": false
        },
        "#8 INDIVIS": {
          "odds": 11.0,
          "tendance": "+",
          "magnitude": 4.38,
          "favoris": false
        }
      }
    },
    "R2/C2": {
      "hippodrome": "COMPIEGNE",
      "label": "PRIX GACKO",
      "heure": "10:17",
      "horses": {
        "#1 ROI DANAOS": {
          "odds": 5.4,
          "tendance": "+",
          "magnitude": 3.84,
          "favoris": true
        },
        "#2 CHATEAU MARMONT": {
          "odds": 9.1,
          "tendance": "-",
          "magnitude": -1.08,
          "favoris": false
        },
        "#3 NEVES DU QUARTIER": {
          "odds": 23.0,
          "tendance": "-",
          "magnitude": -12.96,
          "favoris": false
        },
        "#4 ZAUGUROK": {
          "odds": 6.7,
          "tendance": "-",
          "magnitude": -1.47,
          "favoris": false
        },
        "#5 INFINITY SUN": {
          "odds": 9.1,
          "tendance": "+",
          "magnitude": 1.11,
          "favoris": false
        },
        "#6 PENN KALET": {
          "odds": 10.0,
          "tendance": "+",
          "magnitude": 6.38,
          "favoris": false
        },
        "#7 ADIX": {
          "odds": 9.3,
          "tendance": "+",
          "magnitude": 14.81,
          "favoris": false
        },
        "#8 CHARLY DES BEAUX": {
          "odds": 7.7,
          "tendance": "+",
          "magnitude": 1.31,
          "favoris": false
        },
        "#9 NAJDAM": {
          "odds": 6.6,
          "tendance": "-",
          "magnitude": -16.45,
          "favoris": false
        },
        "#10 THE SINNER": {
          "odds": 14.0,
          "tendance": "+",
          "magnitude": 3.7,
          "favoris": false
        },
        "#11 SO WATH": {
          "odds": 72.0,
          "tendance": "+",
          "magnitude": 8.4,
          "favoris": false
        }
      }
    },
    "R2/C3": {
      "hippodrome": "COMPIEGNE",
      "label": "PRIX MIROR",
      "heure": "10:52",
      "horses": {
        "#1 SAINT CRYSTAL": {
          "odds": 12.0,
          "tendance": "+",
          "magnitude": 7.75,
          "favoris": false
        },
        "#2 NIKKALUOKTA": {
          "odds": 9.0,
          "tendance": "+",
          "magnitude": 20.0,
          "favoris": false
        },
        "#3 LOWELL": {
          "odds": 3.7,
          "tendance": "-",
          "magnitude": -11.9,
          "favoris": true
        },
        "#4 ANATOLE": {
          "odds": 28.0,
          "tendance": "-",
          "magnitude": -3.44,
          "favoris": false
        },
        "#5 GLADY TIGER": {
          "odds": 9.8,
          "tendance": "+",
          "magnitude": 16.66,
          "favoris": false
        },
        "#6 AL FONCE": {
          "odds": 7.1,
          "tendance": "-",
          "magnitude": -12.34,
          "favoris": false
        },
        "#7 MISS CHANA": {
          "odds": 10.0,
          "tendance": "+",
          "magnitude": 4.08,
          "favoris": false
        },
        "#8 MIKI BILLY": {
          "odds": 22.0,
          "tendance": "-",
          "magnitude": -5.78,
          "favoris": false
        },
        "#9 OPERA LIGHT": {
          "odds": 5.5,
          "tendance": "",
          "magnitude": 0.0,
          "favoris": false
        },
        "#10 MORGANE DU LARGE": {
          "odds": 9.1,
          "tendance": "+",
          "magnitude": 4.59,
          "favoris": false
        }
      }
    },
    "R2/C4": {
      "hippodrome": "COMPIEGNE",
      "label": "PRIX ROMATI",
      "heure": "11:27",
      "horses": {
        "#1 GAME OF STORM": {
          "odds": 1.9,
          "tendance": "-",
          "magnitude": -5.0,
          "favoris": true
        },
        "#2 KAMARO D'HUEZ": {
          "odds": 24.0,
          "tendance": "+",
          "magnitude": 8.55,
          "favoris": false
        },
        "#3 LE PHILOSOPHE": {
          "odds": 8.6,
          "tendance": "+",
          "magnitude": 13.15,
          "favoris": false
        },
        "#4 WHYMPER": {
          "odds": 18.0,
          "tendance": "-",
          "magnitude": -9.22,
          "favoris": false
        },
        "#5 JAGUAR DU BERLAIS": {
          "odds": 10.0,
          "tendance": "+",
          "magnitude": 9.47,
          "favoris": false
        },
        "#6 GARDONS LE SOURIRE": {
          "odds": 8.1,
          "tendance": "+",
          "magnitude": 9.45,
          "favoris": false
        },
        "#7 PICKLAND": {
          "odds": 23.0,
          "tendance": "+",
          "magnitude": 8.41,
          "favoris": false
        },
        "#8 VICTORY VALLEY": {
          "odds": 7.7,
          "tendance": "-",
          "magnitude": -9.41,
          "favoris": false
        },
        "#9 PRIAM DU MESNIL": {
          "odds": 17.0,
          "tendance": "+",
          "magnitude": 4.76,
          "favoris": false
        }
      }
    },
    "R2/C5": {
      "hippodrome": "COMPIEGNE",
      "label": "PRIX DU GRAND MAITRE",
      "heure": "12:12",
      "horses": {
        "#1 VALDORINA": {
          "odds": 3.0,
          "tendance": "-",
          "magnitude": -3.22,
          "favoris": true
        },
        "#2 NOBLESS REVEE": {
          "odds": 32.0,
          "tendance": "+",
          "magnitude": 22.98,
          "favoris": false
        },
        "#3 VANEADI": {
          "odds": 41.0,
          "tendance": "-",
          "magnitude": -38.43,
          "favoris": false
        },
        "#4 AZURE MUSE": {
          "odds": 46.0,
          "tendance": "-",
          "magnitude": -4.32,
          "favoris": false
        },
        "#5 NORIASKA": {
          "odds": 6.3,
          "tendance": "+",
          "magnitude": 18.86,
          "favoris": false
        },
        "#6 N'AIE PEUR DE RIEN": {
          "odds": 6.7,
          "tendance": "-",
          "magnitude": -8.21,
          "favoris": false
        },
        "#7 KAMALA": {
          "odds": 4.1,
          "tendance": "-",
          "magnitude": -8.88,
          "favoris": false
        },
        "#8 WASS UP": {
          "odds": 11.0,
          "tendance": "+",
          "magnitude": 6.6,
          "favoris": false
        },
        "#9 LILY DE LA LONDE": {
          "odds": 27.0,
          "tendance": "+",
          "magnitude": 14.87,
          "favoris": false
        },
        "#10 TINOPASA": {
          "odds": 19.0,
          "tendance": "+",
          "magnitude": 11.79,
          "favoris": false
        },
        "#11 AMERICA'S CUP": {
          "odds": 29.0,
          "tendance": "+",
          "magnitude": 23.14,
          "favoris": false
        }
      }
    },
    "R2/C6": {
      "hippodrome": "COMPIEGNE",
      "label": "PRIX HYERES III",
      "heure": "12:47",
      "horses": {
        "#1 MARCHE AVANT": {
          "odds": 9.9,
          "tendance": "-",
          "magnitude": -15.38,
          "favoris": false
        },
        "#2 MACAREL": {
          "odds": 42.0,
          "tendance": "-",
          "magnitude": -18.14,
          "favoris": false
        },
        "#3 BOURBONNAIS": {
          "odds": 11.0,
          "tendance": "-",
          "magnitude": -11.85,
          "favoris": false
        },
        "#4 DREAM FLOWER": {
          "odds": 8.4,
          "tendance": "+",
          "magnitude": 16.66,
          "favoris": false
        },
        "#5 ESPRIT DE LA FORET": {
          "odds": 21.0,
          "tendance": "+",
          "magnitude": 23.25,
          "favoris": false
        },
        "#6 LA ROSERAIE": {
          "odds": 3.5,
          "tendance": "-",
          "magnitude": -7.89,
          "favoris": true
        },
        "#7 PACHA DES BEAUX": {
          "odds": 11.0,
          "tendance": "+",
          "magnitude": 7.2,
          "favoris": false
        },
        "#8 SKY WAY": {
          "odds": 21.0,
          "tendance": "-",
          "magnitude": -4.5,
          "favoris": false
        },
        "#9 STANISLAW": {
          "odds": 27.0,
          "tendance": "+",
          "magnitude": 5.4,
          "favoris": false
        },
        "#10 PAREIL PAREIL": {
          "odds": 19.0,
          "tendance": "+",
          "magnitude": 23.22,
          "favoris": false
        },
        "#11 MON VIEUX JEAN": {
          "odds": 23.0,
          "tendance": "+",
          "magnitude": 7.65,
          "favoris": false
        },
        "#12 MIMILE SOUL": {
          "odds": 18.0,
          "tendance": "+",
          "magnitude": 22.97,
          "favoris": false
        },
        "#13 GOOD FORTUNE": {
          "odds": 9.6,
          "tendance": "-",
          "magnitude": -27.27,
          "favoris": false
        },
        "#14 NORTIA": {
          "odds": 10.0,
          "tendance": "+",
          "magnitude": 12.37,
          "favoris": false
        }
      }
    },
    "R2/C7": {
      "hippodrome": "COMPIEGNE",
      "label": "PRIX FILS DE REINE",
      "heure": "13:22",
      "horses": {
        "#1 LE GENE BLEU": {
          "odds": 19.0,
          "tendance": "+",
          "magnitude": 16.07,
          "favoris": false
        },
        "#2 UNDENIABLE ALIBI": {
          "odds": 44.0,
          "tendance": "+",
          "magnitude": 42.85,
          "favoris": false
        },
        "#3 STARVINA": {
          "odds": 16.0,
          "tendance": "+",
          "magnitude": 21.21,
          "favoris": false
        },
        "#4 LA GACHERE": {
          "odds": 11.0,
          "tendance": "+",
          "magnitude": 15.0,
          "favoris": false
        },
        "#5 FAN D'APPLE'S": {
          "odds": 25.0,
          "tendance": "+",
          "magnitude": 29.38,
          "favoris": false
        },
        "#6 JOCASTA": {
          "odds": 15.0,
          "tendance": "+",
          "magnitude": 43.8,
          "favoris": false
        },
        "#7 BUBBLE PRETTY": {
          "odds": 33.0,
          "tendance": "-",
          "magnitude": -55.4,
          "favoris": false
        },
        "#8 ROYAL LOUIS HAS": {
          "odds": 8.4,
          "tendance": "+",
          "magnitude": 21.73,
          "favoris": false
        },
        "#9 LOLITA SEI": {
          "odds": 6.3,
          "tendance": "+",
          "magnitude": 21.15,
          "favoris": false
        },
        "#10 TUTTI BELLA": {
          "odds": 16.0,
          "tendance": "+",
          "magnitude": 29.92,
          "favoris": false
        },
        "#11 WALKS LIKE THE MAN": {
          "odds": 13.0,
          "tendance": "+",
          "magnitude": 21.23,
          "favoris": false
        },
        "#12 ONE STORY": {
          "odds": 44.0,
          "tendance": "+",
          "magnitude": 42.85,
          "favoris": false
        },
        "#13 ZANHOWE": {
          "odds": 19.0,
          "tendance": "+",
          "magnitude": 21.87,
          "favoris": false
        },
        "#14 JIKITO": {
          "odds": 4.1,
          "tendance": "-",
          "magnitude": -76.7,
          "favoris": true
        },
        "#15 CARGO DE NUIT": {
          "odds": 5.9,
          "tendance": "+",
          "magnitude": 9.25,
          "favoris": false
        }
      }
    },
    "R3/C1": {
      "hippodrome": "MESLAY DU MAINE",
      "label": "PRIX PARIS TURF",
      "heure": "14:52",
      "horses": {
        "#1 LUDMILLA HAUFOR": {
          "odds": 27.0,
          "tendance": "-",
          "magnitude": -44.28,
          "favoris": false
        },
        "#2 LA RIVER D'ECCAM": {
          "odds": 14.0,
          "tendance": "+",
          "magnitude": 1.36,
          "favoris": false
        },
        "#3 LILOU TREMBLADAISE": {
          "odds": 10.0,
          "tendance": "+",
          "magnitude": 20.45,
          "favoris": false
        },
        "#4 LAGHERTHA DU PONT": {
          "odds": 7.4,
          "tendance": "-",
          "magnitude": -25.99,
          "favoris": false
        },
        "#5 LUCRECE HAUFOR": {
          "odds": 13.0,
          "tendance": "+",
          "magnitude": 19.29,
          "favoris": false
        },
        "#6 LIO D'AVEL": {
          "odds": 3.2,
          "tendance": "-",
          "magnitude": -5.88,
          "favoris": true
        },
        "#7 LAIKA DU LEARD": {
          "odds": 8.8,
          "tendance": "",
          "magnitude": 0.0,
          "favoris": false
        },
        "#8 LADY FAIRY": {
          "odds": 11.0,
          "tendance": "",
          "magnitude": 0.0,
          "favoris": false
        },
        "#9 LOUISIANE PARIS": {
          "odds": 5.0,
          "tendance": "+",
          "magnitude": 16.27,
          "favoris": false
        },
        "#10 LOLA DE CHENU": {
          "odds": 18.0,
          "tendance": "+",
          "magnitude": 6.43,
          "favoris": false
        }
      }
    },
    "R3/C2": {
      "hippodrome": "MESLAY DU MAINE",
      "label": "PRIX DU MUGUET",
      "heure": "15:27",
      "horses": {
        "#1 LAIOS DU GOUTIER": {
          "odds": 202.0,
          "tendance": "+",
          "magnitude": 17.92,
          "favoris": false
        },
        "#2 LOTUS MADRIK": {
          "odds": 11.0,
          "tendance": "-",
          "magnitude": -2.45,
          "favoris": false
        },
        "#3 LEIPZIG TEK": {
          "odds": 5.9,
          "tendance": "+",
          "magnitude": 13.46,
          "favoris": false
        },
        "#4 LISSANDRO D'ARC": {
          "odds": 25.0,
          "tendance": "+",
          "magnitude": 3.26,
          "favoris": false
        },
        "#5 LEWIS DE GINAI": {
          "odds": 36.0,
          "tendance": "+",
          "magnitude": 17.94,
          "favoris": false
        },
        "#6 LAMA DE CORDAY": {
          "odds": 10.0,
          "tendance": "-",
          "magnitude": -0.93,
          "favoris": false
        },
        "#7 LOOKING BEST": {
          "odds": 15.0,
          "tendance": "+",
          "magnitude": 4.89,
          "favoris": false
        },
        "#8 LULU THICEMA": {
          "odds": 6.4,
          "tendance": "",
          "magnitude": 0.0,
          "favoris": false
        },
        "#9 LUIGI PAULCA": {
          "odds": 5.4,
          "tendance": "-",
          "magnitude": -14.28,
          "favoris": false
        },
        "#10 LOCKED UP": {
          "odds": 101.0,
          "tendance": "+",
          "magnitude": 17.92,
          "favoris": false
        },
        "#11 LOOK PEJI": {
          "odds": 3.0,
          "tendance": "",
          "magnitude": 0.0,
          "favoris": true
        }
      }
    },
    "R3/C3": {
      "hippodrome": "MESLAY DU MAINE",
      "label": "PRIX V AND B - VINS ET BIERES",
      "heure": "16:02",
      "horses": {
        "#1 KIMONO JULRY": {
          "odds": 6.3,
          "tendance": "+",
          "magnitude": 10.52,
          "favoris": false
        },
        "#2 KOALA DES ARCS": {
          "odds": 12.0,
          "tendance": "-",
          "magnitude": -1.61,
          "favoris": false
        },
        "#3 KENZO D'EVA": {
          "odds": 8.9,
          "tendance": "",
          "magnitude": 0.0,
          "favoris": false
        },
        "#4 KENJI D'AUBERVILLE": {
          "odds": 13.0,
          "tendance": "-",
          "magnitude": -8.33,
          "favoris": false
        },
        "#5 KENTUCKY DANICA": {
          "odds": 4.4,
          "tendance": "+",
          "magnitude": 2.32,
          "favoris": true
        },
        "#6 JOLLITY GABY": {
          "odds": 22.0,
          "tendance": "-",
          "magnitude": -10.08,
          "favoris": false
        },
        "#7 JINGLE PACA": {
          "odds": 14.0,
          "tendance": "",
          "magnitude": 0.0,
          "favoris": false
        },
        "#8 KEPHYR D'ESTE": {
          "odds": 5.7,
          "tendance": "+",
          "magnitude": 9.61,
          "favoris": false
        },
        "#9 JAKA DU RUEL": {
          "odds": 9.6,
          "tendance": "-",
          "magnitude": -24.4,
          "favoris": false
        },
        "#10 JAZZY JOSSELYN": {
          "odds": 8.1,
          "tendance": "+",
          "magnitude": 2.53,
          "favoris": false
        }
      }
    },
    "R3/C4": {
      "hippodrome": "MESLAY DU MAINE",
      "label": "PRIX DU PRINTEMPS",
      "heure": "16:37",
      "horses": {
        "#1 KANSAS DU HOCTI": {
          "odds": 356.0,
          "tendance": "",
          "magnitude": 0.0,
          "favoris": false
        },
        "#2 HIT PERRINE": {
          "odds": 59.0,
          "tendance": "-",
          "magnitude": -4.34,
          "favoris": false
        },
        "#3 KASSYA": {
          "odds": 35.0,
          "tendance": "-",
          "magnitude": -19.81,
          "favoris": false
        },
        "#4 HANACK DE VIVOIN": {
          "odds": 20.0,
          "tendance": "+",
          "magnitude": 0.96,
          "favoris": false
        },
        "#5 KHEO VIVANCIERE": {
          "odds": 10.0,
          "tendance": "-",
          "magnitude": -8.47,
          "favoris": false
        },
        "#6 KING LOOK": {
          "odds": 2.3,
          "tendance": "-",
          "magnitude": -8.0,
          "favoris": false
        },
        "#7 KESITO D'URVILLE": {
          "odds": 2.2,
          "tendance": "+",
          "magnitude": 15.78,
          "favoris": true
        },
        "#8 HARDY DES LANDES": {
          "odds": 118.0,
          "tendance": "-",
          "magnitude": -23.55,
          "favoris": false
        },
        "#9 JASPE DU DOLLAR": {
          "odds": 10.0,
          "tendance": "+",
          "magnitude": 6.99,
          "favoris": false
        }
      }
    },
    "R3/C5": {
      "hippodrome": "MESLAY DU MAINE",
      "label": "PRIX LANCELOT",
      "heure": "17:12",
      "horses": {
        "#1 MELODY DU DIGEON": {
          "odds": 102.0,
          "tendance": "-",
          "magnitude": -40.91,
          "favoris": false
        },
        "#2 MAJESTY D'EOLE": {
          "odds": 137.0,
          "tendance": "+",
          "magnitude": 18.1,
          "favoris": false
        },
        "#3 MANON DU RIED": {
          "odds": 41.0,
          "tendance": "+",
          "magnitude": 18.1,
          "favoris": false
        },
        "#4 MAGIC MAGGIE": {
          "odds": 21.0,
          "tendance": "+",
          "magnitude": 5.88,
          "favoris": false
        },
        "#5 MOON IN THE SKY": {
          "odds": 82.0,
          "tendance": "-",
          "magnitude": -76.37,
          "favoris": false
        },
        "#6 MERRY DE MALABRY": {
          "odds": 3.8,
          "tendance": "+",
          "magnitude": 11.76,
          "favoris": false
        },
        "#7 MARA DU SAPHIR": {
          "odds": 5.4,
          "tendance": "-",
          "magnitude": -15.62,
          "favoris": false
        },
        "#8 MANON DU CHENE": {
          "odds": 58.0,
          "tendance": "+",
          "magnitude": 18.1,
          "favoris": false
        },
        "#9 MALIKA DU SURF": {
          "odds": 16.0,
          "tendance": "-",
          "magnitude": -5.74,
          "favoris": false
        },
        "#10 MANOLA DE MUZE": {
          "odds": 21.0,
          "tendance": "+",
          "magnitude": 5.88,
          "favoris": false
        },
        "#11 MARIE CHARLOTTE": {
          "odds": 13.0,
          "tendance": "-",
          "magnitude": -29.01,
          "favoris": false
        },
        "#12 MAYA D'AUBRIERE": {
          "odds": 3.0,
          "tendance": "+",
          "magnitude": 7.14,
          "favoris": true
        },
        "#13 MIA DE SIMM": {
          "odds": 24.0,
          "tendance": "-",
          "magnitude": -9.73,
          "favoris": false
        },
        "#14 MARVELOUS PIYA": {
          "odds": 17.0,
          "tendance": "-",
          "magnitude": -16.17,
          "favoris": false
        }
      }
    },
    "R3/C6": {
      "hippodrome": "MESLAY DU MAINE",
      "label": "PRIX DU CONCOURS D'ATTELAGE DE MESLAY",
      "heure": "17:47",
      "horses": {
        "#1 MELMETAL": {
          "odds": 29.0,
          "tendance": "-",
          "magnitude": -31.05,
          "favoris": false
        },
        "#2 MELICIANO": {
          "odds": 7.3,
          "tendance": "+",
          "magnitude": 4.28,
          "favoris": false
        },
        "#3 MEGA D'UZE": {
          "odds": 8.3,
          "tendance": "+",
          "magnitude": 7.79,
          "favoris": false
        },
        "#4 MADRAS": {
          "odds": 3.3,
          "tendance": "-",
          "magnitude": -17.5,
          "favoris": false
        },
        "#5 MILLESIME GWEN": {
          "odds": 2.4,
          "tendance": "-",
          "magnitude": -4.0,
          "favoris": true
        },
        "#6 MILANO DARLING": {
          "odds": 9.7,
          "tendance": "+",
          "magnitude": 38.57,
          "favoris": false
        },
        "#7 MILKSHAKE": {
          "odds": 16.0,
          "tendance": "+",
          "magnitude": 38.01,
          "favoris": false
        }
      }
    },
    "R3/C7": {
      "hippodrome": "MESLAY DU MAINE",
      "label": "PRIX DE LA PAUBELIERE",
      "heure": "18:20",
      "horses": {
        "#1 NICOS BLEU": {
          "odds": 9.9,
          "tendance": "+",
          "magnitude": 16.47,
          "favoris": false
        },
        "#2 NAPOLEON DE GAGOU": {
          "odds": 2.0,
          "tendance": "-",
          "magnitude": -4.76,
          "favoris": true
        },
        "#3 NINJA DU PLESSIS": {
          "odds": 10.0,
          "tendance": "+",
          "magnitude": 0.95,
          "favoris": false
        },
        "#4 NOBLE DU SURF": {
          "odds": 9.3,
          "tendance": "+",
          "magnitude": 2.19,
          "favoris": false
        },
        "#5 NIERMES DE GUEZ": {
          "odds": 7.2,
          "tendance": "+",
          "magnitude": 14.28,
          "favoris": false
        },
        "#6 NUAGE DIVIN": {
          "odds": 13.0,
          "tendance": "+",
          "magnitude": 15.78,
          "favoris": false
        },
        "#7 NAPOLEON": {
          "odds": 12.0,
          "tendance": "-",
          "magnitude": -19.73,
          "favoris": false
        },
        "#8 NELSON FAFA": {
          "odds": 22.0,
          "tendance": "-",
          "magnitude": -17.15,
          "favoris": false
        },
        "#9 NIARKOS DU CEBE": {
          "odds": 22.0,
          "tendance": "-",
          "magnitude": -33.62,
          "favoris": false
        }
      }
    },
    "R3/C8": {
      "hippodrome": "MESLAY DU MAINE",
      "label": "PRIX DE LA TOUCHE",
      "heure": "18:45",
      "horses": {
        "#1 LEO DES KECHES": {
          "odds": 4.9,
          "tendance": "+",
          "magnitude": 8.88,
          "favoris": false
        },
        "#2 LAGOS DE VAL": {
          "odds": 4.8,
          "tendance": "+",
          "magnitude": 11.62,
          "favoris": false
        },
        "#3 LIVIA DES LANDES": {
          "odds": 13.0,
          "tendance": "+",
          "magnitude": 14.16,
          "favoris": false
        },
        "#4 LADY SARAH": {
          "odds": 9.8,
          "tendance": "-",
          "magnitude": -10.09,
          "favoris": false
        },
        "#5 LOU DES COUPERIES": {
          "odds": 15.0,
          "tendance": "+",
          "magnitude": 4.72,
          "favoris": false
        },
        "#6 LEON DE LA COURBE": {
          "odds": 9.4,
          "tendance": "+",
          "magnitude": 9.3,
          "favoris": false
        },
        "#7 LEON DU CLOS": {
          "odds": 12.0,
          "tendance": "-",
          "magnitude": -1.59,
          "favoris": false
        },
        "#8 LOOK AT ME LULU": {
          "odds": 6.8,
          "tendance": "-",
          "magnitude": -56.41,
          "favoris": false
        },
        "#9 LUCIA PERRINE": {
          "odds": 19.0,
          "tendance": "-",
          "magnitude": -17.08,
          "favoris": false
        },
        "#10 LACIENDA FLASH": {
          "odds": 4.2,
          "tendance": "+",
          "magnitude": 13.51,
          "favoris": true
        }
      }
    },
    "R4/C1": {
      "hippodrome": "CHANTILLY",
      "label": "PRIX DU MONT DE PO",
      "heure": "13:57",
      "horses": {
        "#1 LAMEGO": {
          "odds": 15.0,
          "tendance": "-",
          "magnitude": -5.62,
          "favoris": false
        },
        "#2 MAITRE JIMMY": {
          "odds": 11.0,
          "tendance": "-",
          "magnitude": -6.55,
          "favoris": false
        },
        "#3 INCREDIBLE": {
          "odds": 13.0,
          "tendance": "+",
          "magnitude": 9.24,
          "favoris": false
        },
        "#4 SACREE PHILOMENE": {
          "odds": 3.8,
          "tendance": "-",
          "magnitude": -15.55,
          "favoris": true
        },
        "#5 RENOUVEAU": {
          "odds": 5.7,
          "tendance": "+",
          "magnitude": 1.78,
          "favoris": false
        },
        "#6 SHE'S BOX OFFICE": {
          "odds": 19.0,
          "tendance": "+",
          "magnitude": 24.51,
          "favoris": false
        },
        "#7 PARTIE ROCKET": {
          "odds": 11.0,
          "tendance": "",
          "magnitude": 0.0,
          "favoris": false
        },
        "#8 ARALIA": {
          "odds": 8.5,
          "tendance": "-",
          "magnitude": -21.29,
          "favoris": false
        },
        "#9 ROYAL RIZZI": {
          "odds": 12.0,
          "tendance": "+",
          "magnitude": 20.38,
          "favoris": false
        },
        "#10 FERRA CHOPE": {
          "odds": 26.0,
          "tendance": "+",
          "magnitude": 24.29,
          "favoris": false
        },
        "#11 TSUNAMIA": {
          "odds": 8.0,
          "tendance": "+",
          "magnitude": 23.07,
          "favoris": false
        }
      }
    },
    "R4/C2": {
      "hippodrome": "CHANTILLY",
      "label": "PRIX DE GUICHE",
      "heure": "14:35",
      "horses": {
        "#1 LORD CLOVER": {
          "odds": 10.0,
          "tendance": "+",
          "magnitude": 6.93,
          "favoris": false
        },
        "#2 HAWK MOUNTAIN": {
          "odds": 1.9,
          "tendance": "+",
          "magnitude": 18.74,
          "favoris": true
        },
        "#3 CAMPACITE": {
          "odds": 2.7,
          "tendance": "-",
          "magnitude": -24.99,
          "favoris": false
        },
        "#4 PARADE BAY": {
          "odds": 8.1,
          "tendance": "+",
          "magnitude": 9.45,
          "favoris": false
        },
        "#5 MR LOPE CEN": {
          "odds": 16.0,
          "tendance": "+",
          "magnitude": 0.62,
          "favoris": false
        }
      }
    },
    "R4/C3": {
      "hippodrome": "CHANTILLY",
      "label": "PRIX DES LILAS",
      "heure": "15:10",
      "horses": {
        "#1 EOSTRE": {
          "odds": 8.7,
          "tendance": "-",
          "magnitude": -9.37,
          "favoris": false
        },
        "#2 EDAJA": {
          "odds": 2.6,
          "tendance": "",
          "magnitude": 0.0,
          "favoris": true
        },
        "#3 HOUVILLE": {
          "odds": 11.0,
          "tendance": "+",
          "magnitude": 1.85,
          "favoris": false
        },
        "#4 ECIJA": {
          "odds": 12.0,
          "tendance": "+",
          "magnitude": 1.57,
          "favoris": false
        },
        "#5 AHALYA": {
          "odds": 25.0,
          "tendance": "+",
          "magnitude": 7.23,
          "favoris": false
        },
        "#6 INSIDIA": {
          "odds": 21.0,
          "tendance": "-",
          "magnitude": -1.4,
          "favoris": false
        },
        "#7 PIERCHIC": {
          "odds": 2.6,
          "tendance": "",
          "magnitude": 0.0,
          "favoris": true
        },
        "#9 STIMULATIVE TRIP": {
          "odds": 25.0,
          "tendance": "-",
          "magnitude": -3.44,
          "favoris": false
        }
      }
    },
    "R4/C4": {
      "hippodrome": "CHANTILLY",
      "label": "PRIX DE BARBERY",
      "heure": "15:45",
      "horses": {
        "#1 BURATTINA": {
          "odds": 36.0,
          "tendance": "-",
          "magnitude": -20.86,
          "favoris": false
        },
        "#2 MON SCHATZI": {
          "odds": 19.0,
          "tendance": "+",
          "magnitude": 3.76,
          "favoris": false
        },
        "#3 REAL SOCIEDAD": {
          "odds": 13.0,
          "tendance": "-",
          "magnitude": -2.17,
          "favoris": false
        },
        "#4 JOYEUSE SAGE": {
          "odds": 8.6,
          "tendance": "+",
          "magnitude": 11.68,
          "favoris": false
        },
        "#5 SEIGNEUR": {
          "odds": 4.6,
          "tendance": "-",
          "magnitude": -2.12,
          "favoris": true
        },
        "#6 SORENGO": {
          "odds": 41.0,
          "tendance": "+",
          "magnitude": 19.08,
          "favoris": false
        },
        "#7 BOLZANO": {
          "odds": 8.0,
          "tendance": "+",
          "magnitude": 6.66,
          "favoris": false
        },
        "#8 AMOUAGE": {
          "odds": 43.0,
          "tendance": "+",
          "magnitude": 19.11,
          "favoris": false
        },
        "#9 COMTE NOIR": {
          "odds": 9.6,
          "tendance": "-",
          "magnitude": -2.04,
          "favoris": false
        },
        "#10 BRAVE SHIINA": {
          "odds": 18.0,
          "tendance": "-",
          "magnitude": -11.33,
          "favoris": false
        },
        "#11 ANTINEA": {
          "odds": 11.0,
          "tendance": "-",
          "magnitude": -35.0,
          "favoris": false
        },
        "#12 MONTE LINAS": {
          "odds": 20.0,
          "tendance": "+",
          "magnitude": 6.28,
          "favoris": false
        },
        "#13 MOON RIDER": {
          "odds": 21.0,
          "tendance": "+",
          "magnitude": 12.56,
          "favoris": false
        },
        "#14 LA DOLOISE": {
          "odds": 32.0,
          "tendance": "-",
          "magnitude": -25.8,
          "favoris": false
        },
        "#15 OASIS BAY": {
          "odds": 10.0,
          "tendance": "+",
          "magnitude": 7.21,
          "favoris": false
        },
        "#16 PRINCESSE BLONDE": {
          "odds": 22.0,
          "tendance": "+",
          "magnitude": 12.18,
          "favoris": false
        }
      }
    },
    "R4/C5": {
      "hippodrome": "CHANTILLY",
      "label": "PRIX DU CERFOUILLET",
      "heure": "16:20",
      "horses": {
        "#1 VIZIOSA": {
          "odds": 19.0,
          "tendance": "+",
          "magnitude": 6.7,
          "favoris": false
        },
        "#2 OSHIA": {
          "odds": 41.0,
          "tendance": "+",
          "magnitude": 4.77,
          "favoris": false
        },
        "#3 ZENADIA": {
          "odds": 13.0,
          "tendance": "+",
          "magnitude": 24.99,
          "favoris": false
        },
        "#4 GO KEN GO": {
          "odds": 10.0,
          "tendance": "+",
          "magnitude": 16.85,
          "favoris": false
        },
        "#5 ELEGANTE WOMAN": {
          "odds": 11.0,
          "tendance": "+",
          "magnitude": 21.5,
          "favoris": false
        },
        "#6 RASSENI CHOP": {
          "odds": 41.0,
          "tendance": "-",
          "magnitude": -6.91,
          "favoris": false
        },
        "#7 VEGA MEMORIES": {
          "odds": 35.0,
          "tendance": "+",
          "magnitude": 18.06,
          "favoris": false
        },
        "#8 ZAHARA": {
          "odds": 6.8,
          "tendance": "+",
          "magnitude": 11.47,
          "favoris": false
        },
        "#9 SBIKHA": {
          "odds": 11.0,
          "tendance": "+",
          "magnitude": 21.27,
          "favoris": false
        },
        "#10 HOLLIE WOOD": {
          "odds": 18.0,
          "tendance": "+",
          "magnitude": 17.3,
          "favoris": false
        },
        "#11 SUGAR DADDY": {
          "odds": 5.8,
          "tendance": "-",
          "magnitude": -69.14,
          "favoris": true
        },
        "#12 TINMANDER": {
          "odds": 13.0,
          "tendance": "-",
          "magnitude": -2.79,
          "favoris": false
        },
        "#13 THIBERVILLE": {
          "odds": 8.6,
          "tendance": "+",
          "magnitude": 22.85,
          "favoris": false
        },
        "#14 PERFECT MOON": {
          "odds": 13.0,
          "tendance": "-",
          "magnitude": -8.39,
          "favoris": false
        },
        "#15 NIOUININON": {
          "odds": 229.0,
          "tendance": "+",
          "magnitude": 28.03,
          "favoris": false
        },
        "#16 IGETAKICKOUTOFYOU": {
          "odds": 19.0,
          "tendance": "-",
          "magnitude": -11.16,
          "favoris": false
        }
      }
    },
    "R4/C6": {
      "hippodrome": "CHANTILLY",
      "label": "PRIX DE BOREST",
      "heure": "16:55",
      "horses": {
        "#1 CARLSTON": {
          "odds": 22.0,
          "tendance": "+",
          "magnitude": 10.94,
          "favoris": false
        },
        "#2 MISTER JULES": {
          "odds": 23.0,
          "tendance": "-",
          "magnitude": -34.07,
          "favoris": false
        },
        "#3 SICILIA": {
          "odds": 26.0,
          "tendance": "-",
          "magnitude": -15.21,
          "favoris": false
        },
        "#4 POKROV": {
          "odds": 13.0,
          "tendance": "-",
          "magnitude": -42.5,
          "favoris": false
        },
        "#5 ESKANDANI": {
          "odds": 5.5,
          "tendance": "+",
          "magnitude": 17.02,
          "favoris": true
        },
        "#6 DON NIKOLAOS": {
          "odds": 32.0,
          "tendance": "-",
          "magnitude": -24.24,
          "favoris": false
        },
        "#7 FECAMP": {
          "odds": 7.1,
          "tendance": "-",
          "magnitude": -7.79,
          "favoris": false
        },
        "#8 LOOK OF CECCA": {
          "odds": 43.0,
          "tendance": "+",
          "magnitude": 0.92,
          "favoris": false
        },
        "#9 DARIYANGEL": {
          "odds": 7.1,
          "tendance": "+",
          "magnitude": 5.97,
          "favoris": false
        },
        "#10 MAGIC STARS": {
          "odds": 9.3,
          "tendance": "+",
          "magnitude": 16.25,
          "favoris": false
        },
        "#11 BORCANO": {
          "odds": 11.0,
          "tendance": "-",
          "magnitude": -9.75,
          "favoris": false
        },
        "#12 ROYAL RIGHT": {
          "odds": 65.0,
          "tendance": "-",
          "magnitude": -54.6,
          "favoris": false
        },
        "#13 BAILEYS ECLAIR": {
          "odds": 47.0,
          "tendance": "-",
          "magnitude": -0.83,
          "favoris": false
        },
        "#14 SECOND TO NONE": {
          "odds": 7.8,
          "tendance": "+",
          "magnitude": 6.84,
          "favoris": false
        },
        "#15 JOUKOVKA": {
          "odds": 15.0,
          "tendance": "+",
          "magnitude": 14.38,
          "favoris": false
        },
        "#16 NEBUCHADNASSER": {
          "odds": 30.0,
          "tendance": "+",
          "magnitude": 21.17,
          "favoris": false
        }
      }
    },
    "R4/C7": {
      "hippodrome": "CHANTILLY",
      "label": "PRIX SERVANNE",
      "heure": "17:30",
      "horses": {
        "#1 SAJIR": {
          "odds": 3.1,
          "tendance": "-",
          "magnitude": -27.9,
          "favoris": false
        },
        "#2 STOLEN KISS": {
          "odds": 11.0,
          "tendance": "+",
          "magnitude": 7.4,
          "favoris": false
        },
        "#3 MISE EN BOITE": {
          "odds": 10.0,
          "tendance": "-",
          "magnitude": -55.69,
          "favoris": false
        },
        "#4 VICTORY CALL": {
          "odds": 10.0,
          "tendance": "+",
          "magnitude": 23.86,
          "favoris": false
        },
        "#5 CHARIBELLE": {
          "odds": 12.0,
          "tendance": "-",
          "magnitude": -9.09,
          "favoris": false
        },
        "#6 PROFUMO DI IENA": {
          "odds": 15.0,
          "tendance": "+",
          "magnitude": 11.11,
          "favoris": false
        },
        "#7 ALREYYAH": {
          "odds": 15.0,
          "tendance": "+",
          "magnitude": 10.07,
          "favoris": false
        },
        "#8 MEDITERANNIO": {
          "odds": 2.8,
          "tendance": "+",
          "magnitude": 33.33,
          "favoris": true
        }
      }
    },
    "R4/C8": {
      "hippodrome": "CHANTILLY",
      "label": "PRIX DE BARON",
      "heure": "18:05",
      "horses": {
        "#1 CLOUD MAN": {
          "odds": 22.0,
          "tendance": "+",
          "magnitude": 33.33,
          "favoris": false
        },
        "#2 ZOUBAREVA": {
          "odds": 37.0,
          "tendance": "-",
          "magnitude": -21.87,
          "favoris": false
        },
        "#3 MARCAN": {
          "odds": 9.1,
          "tendance": "+",
          "magnitude": 29.99,
          "favoris": false
        },
        "#4 GOLDEN TRIP": {
          "odds": 23.0,
          "tendance": "-",
          "magnitude": -1.66,
          "favoris": false
        },
        "#5 TWIN DREAM": {
          "odds": 14.0,
          "tendance": "+",
          "magnitude": 5.83,
          "favoris": false
        },
        "#6 ZYGFRYD": {
          "odds": 3.0,
          "tendance": "-",
          "magnitude": -50.0,
          "favoris": true
        },
        "#7 YOUM IN LOVE": {
          "odds": 13.0,
          "tendance": "+",
          "magnitude": 24.54,
          "favoris": false
        },
        "#8 ZAADOR": {
          "odds": 21.0,
          "tendance": "-",
          "magnitude": -19.92,
          "favoris": false
        },
        "#9 MAGURO": {
          "odds": 49.0,
          "tendance": "+",
          "magnitude": 33.06,
          "favoris": false
        },
        "#10 SECRET GLORY": {
          "odds": 106.0,
          "tendance": "+",
          "magnitude": 33.12,
          "favoris": false
        },
        "#11 CHONBURI": {
          "odds": 26.0,
          "tendance": "+",
          "magnitude": 10.83,
          "favoris": false
        },
        "#12 KARAWAN": {
          "odds": 31.0,
          "tendance": "+",
          "magnitude": 19.92,
          "favoris": false
        },
        "#13 MAESTRO CHOP": {
          "odds": 9.8,
          "tendance": "+",
          "magnitude": 28.94,
          "favoris": false
        },
        "#14 RED CRAZY": {
          "odds": 8.5,
          "tendance": "+",
          "magnitude": 26.86,
          "favoris": false
        },
        "#15 ALVAR": {
          "odds": 106.0,
          "tendance": "+",
          "magnitude": 33.12,
          "favoris": false
        },
        "#16 LA MOMY": {
          "odds": 10.0,
          "tendance": "+",
          "magnitude": 24.69,
          "favoris": false
        }
      }
    }
  }
}